odoo/addons/stock_location_last_inventory_date/README.rst
odoo/addons/stock_location_last_inventory_date/__init__.py
odoo/addons/stock_location_last_inventory_date/__manifest__.py
odoo/addons/stock_location_last_inventory_date/i18n/stock_location_last_inventory_date.pot
odoo/addons/stock_location_last_inventory_date/models/__init__.py
odoo/addons/stock_location_last_inventory_date/models/stock_location.py
odoo/addons/stock_location_last_inventory_date/readme/CONTRIBUTORS.rst
odoo/addons/stock_location_last_inventory_date/readme/DESCRIPTION.rst
odoo/addons/stock_location_last_inventory_date/static/description/icon.png
odoo/addons/stock_location_last_inventory_date/static/description/index.html
odoo/addons/stock_location_last_inventory_date/tests/__init__.py
odoo/addons/stock_location_last_inventory_date/tests/test_stock_location.py
odoo/addons/stock_location_last_inventory_date/views/stock_location_views.xml
odoo13_addon_stock_location_last_inventory_date-13.0.1.0.1.dist-info/METADATA
odoo13_addon_stock_location_last_inventory_date-13.0.1.0.1.dist-info/WHEEL
odoo13_addon_stock_location_last_inventory_date-13.0.1.0.1.dist-info/top_level.txt
odoo13_addon_stock_location_last_inventory_date-13.0.1.0.1.dist-info/RECORD
